changelog_md/__init__.py
changelog_md/__main__.py
changelog_md/logger.py
changelog_md-0.1.4.dist-info/WHEEL
changelog_md-0.1.4.dist-info/METADATA
changelog_md-0.1.4.dist-info/RECORD
