Metadata-Version: 2.1
Name: changelog-md
Version: 0.1.4
Summary: A package to create changelogs for your git tracked projects.
Home-page: https://github.com/RuslanSergeev/git_changelog
License: MIT
Keywords: markdown,changelog,cicd
Author: Ruslan Sergeev
Author-email: mybox.sergeev@gmail.com
Requires-Python: >=3.7,<4.0
Classifier: License :: OSI Approved :: MIT License
Classifier: Programming Language :: Python :: 3
Classifier: Programming Language :: Python :: 3.7
Classifier: Programming Language :: Python :: 3.8
Classifier: Programming Language :: Python :: 3.9
Project-URL: Repository, https://github.com/RuslanSergeev/git_changelog
